LICENSE
rxwidgets/__init__.py
rxwidgets/contexts.py
rxwidgets/decorators.py
rxwidgets/delegating.py
rxwidgets/ipython/__init__.py
rxwidgets/ipython/automap.py
rxwidgets/ipython/defer.py
rxwidgets/ipython/display.py
rxwidgets/ipython/flatmap.py
rxwidgets/ipython/interact.py
rxwidgets/ipython/load.py
rxwidgets/ipython/pandas/__init__.py
rxwidgets/ipython/pandas/dataframe/__init__.py
rxwidgets/ipython/pandas/dataframe/filter.py
rxwidgets/ipython/pandas/dataframe/select_row.py
rxwidgets/ipython/pandas/paths.py
rxwidgets/ipython/parameters.py
rxwidgets/ipython/screen.py
rxwidgets/ipython/stream.py
rxwidgets/ipython/widgets/__init__.py
rxwidgets/ipython/widgets/observe.py
rxwidgets/ipython/widgets/wrap.py
rxwidgets/rx/__init__.py
rxwidgets/rx/call.py
rxwidgets/valuebox.py
rxwidgets-0.1.10.dist-info/LICENSE
rxwidgets-0.1.10.dist-info/WHEEL
rxwidgets-0.1.10.dist-info/METADATA
rxwidgets-0.1.10.dist-info/RECORD
