Metadata-Version: 2.1
Name: rxwidgets
Version: 0.1.10
Summary: iPython notebooks with reactive UI - powered by RxPy and ipywidgets
Home-page: https://github.com/Ivorforce/rxwidgets
License: MIT
Keywords: ipython,reactivex
Author: Lukas Tenbrink
Author-email: lukas.tenbrink@gmail.com
Requires-Python: >=3.8,<3.11
Classifier: License :: OSI Approved :: MIT License
Classifier: Programming Language :: Python :: 3
Classifier: Programming Language :: Python :: 3.8
Classifier: Programming Language :: Python :: 3.9
Requires-Dist: ipywidgets (>=7.6.3,<8.0.0)
Requires-Dist: reactivex (>=4.0.0,<5.0.0)
Project-URL: Repository, https://github.com/Ivorforce/rxwidgets
